[
    {
        "Page Link": "https://www.npr.org/programs/all-things-considered/1998/10/03/12946897/",
        "Edition": "All Things",
        "Date Numbered": "1998-10-03",
        "Day": "Sat",
        "Scanned Date": "2022-02-06 19:14:34"
    },
    {
        "Title": "Bob Dole",
        "Link": "https://www.npr.org/1998/10/03/1006541/bob-dole",
        "Slug": null,
        "By": null
    },
    {
        "Title": "White House Aides In Docs",
        "Link": "https://www.npr.org/1998/10/03/1006542/white-house-aides-in-docs",
        "Slug": null,
        "By": null
    },
    {
        "Title": "Computers In Schools",
        "Link": "https://www.npr.org/1998/10/03/1006543/computers-in-schools",
        "Slug": null,
        "By": null
    },
    {
        "Title": "Starr Esl Quiz",
        "Link": "https://www.npr.org/1998/10/03/1006544/starr-esl-quiz",
        "Slug": null,
        "By": null
    },
    {
        "Title": "Letters",
        "Link": "https://www.npr.org/1998/10/03/1006545/letters",
        "Slug": null,
        "By": null
    },
    {
        "Title": "Casinos",
        "Link": "https://www.npr.org/1998/10/03/1006546/casinos",
        "Slug": null,
        "By": null
    },
    {
        "Title": "Rainwater",
        "Link": "https://www.npr.org/1998/10/03/1006547/rainwater",
        "Slug": null,
        "By": null
    },
    {
        "Title": "Dr. Laura",
        "Link": "https://www.npr.org/1998/10/03/1006548/dr-laura",
        "Slug": null,
        "By": null
    }
]