[
    {
        "Page Link": "https://www.npr.org/programs/morning-edition/2005/06/14/13013822/",
        "Edition": "Morning Edition",
        "Date Numbered": "2005-06-14",
        "Day": "Tue",
        "Scanned Date": "2021-05-31 22:15:10"
    },
    {
        "Title": "High Court Cites Racial Bias in Overturning Murder Case",
        "Link": "https://www.npr.org/templates/story/story.php?storyId=4702366",
        "Slug": "Law",
        "By": "John Burnett"
    },
    {
        "Title": "Jackson Acquitted, Faces Millions in Debt",
        "Link": "https://www.npr.org/templates/story/story.php?storyId=4702369",
        "Slug": "The Michael Jackson Trial",
        "By": null
    },
    {
        "MoWeEd Track": "Transparence",
        "MoWeEd Artists": [
            "Charlie Haden",
            "Gonzalo Rubalcaba"
        ]
    },
    {
        "MoWeEd Track": "Nocturnal",
        "MoWeEd Artists": [
            "Charlie Haden",
            "Gonzalo Rubalcaba"
        ]
    },
    {
        "Title": "In Rhode Island, a Republican Governor in Democratic Territory",
        "Link": "https://www.npr.org/templates/story/story.php?storyId=4702372",
        "Slug": "Politics",
        "By": "Juan Williams"
    },
    {
        "MoWeEd Track": "Steve's Song",
        "MoWeEd Artists": [
            "Phil Heywood"
        ]
    },
    {
        "MoWeEd Track": "Home Range",
        "MoWeEd Artists": [
            "Phil Heywood"
        ]
    },
    {
        "Title": "Cities Developing Natural Water Parks from Streams",
        "Link": "https://www.npr.org/templates/story/story.php?storyId=4702375",
        "Slug": "National",
        "By": "Jeff Brady"
    },
    {
        "MoWeEd Track": "Marion's Suite for flute & ensemble, Nos 1-5, complete",
        "MoWeEd Artists": [
            "Alain Marion"
        ]
    },
    {
        "Title": "Move to Repeal Italian Assisted Fertility Law Fails",
        "Link": "https://www.npr.org/templates/story/story.php?storyId=4702378",
        "Slug": "World",
        "By": "Sylvia Poggioli"
    },
    {
        "Title": "Europe Struggles to Balance Economy, Social Services",
        "Link": "https://www.npr.org/templates/story/story.php?storyId=4702381",
        "Slug": "Doubts Arise Over EU Constitution",
        "By": "Emily Harris"
    },
    {
        "MoWeEd Track": "The Cat and the Rooster",
        "MoWeEd Artists": [
            "3 Leg Torso"
        ]
    },
    {
        "MoWeEd Track": "The Chimera",
        "MoWeEd Artists": [
            "Ken Hatfield Trio"
        ]
    },
    {
        "Title": "Online Seller eBay Suffers Growing Pains",
        "Link": "https://www.npr.org/templates/story/story.php?storyId=4702384",
        "Slug": "Technology",
        "By": "Laura Sydell"
    },
    {
        "MoWeEd Track": "Alan Corday",
        "MoWeEd Artists": [
            "Chick Corea's Elektric Band"
        ]
    },
    {
        "MoWeEd Track": "Concerto No. 1 for Flute and Orchestra in G Major, K. 313 (285C): III. Rondeau. Tempo di menuetto",
        "MoWeEd Artists": [
            "Shigenori Kudo",
            "Mito Chamber Orchestra",
            "Seiji Ozawa"
        ]
    },
    {
        "Title": "Gallup Poll: Support Falling for War in Iraq",
        "Link": "https://www.npr.org/templates/story/story.php?storyId=4702387",
        "Slug": "World",
        "By": "Vicky O'Hara"
    },
    {
        "Title": "Law Encourages Reporting of Military Sexual Assault",
        "Link": "https://www.npr.org/templates/story/story.php?storyId=4702390",
        "Slug": "Law",
        "By": "Kristin Wiederholt"
    },
    {
        "MoWeEd Track": "Erich Suas a Stoirin",
        "MoWeEd Artists": [
            "Al Petteway"
        ]
    },
    {
        "MoWeEd Track": "Pieces En Concert/la Tromba",
        "MoWeEd Artists": [
            "Trio Concertant"
        ]
    },
    {
        "Title": "Energy Bill Spurs Debate on Ceiling Fans",
        "Link": "https://www.npr.org/templates/story/story.php?storyId=4702393",
        "Slug": "Politics",
        "By": "Kathleen Schalch"
    },
    {
        "Title": "San Francisco Expected to Adopt Green Purchasing Law",
        "Link": "https://www.npr.org/templates/story/story.php?storyId=4702396",
        "Slug": "National",
        "By": "Sarah Varney"
    },
    {
        "MoWeEd Track": "Miles Away",
        "MoWeEd Artists": [
            "Wayman Tisdale"
        ]
    },
    {
        "MoWeEd Track": "Miles Away",
        "MoWeEd Artists": [
            "Wayman Tisdale"
        ]
    },
    {
        "Title": "Schwarzenegger Fights for November Special Election",
        "Link": "https://www.npr.org/templates/story/story.php?storyId=4702399",
        "Slug": "Politics",
        "By": "John Myers"
    },
    {
        "MoWeEd Track": "Pop",
        "MoWeEd Artists": [
            "Los Angeles Guitar Quartet"
        ]
    },
    {
        "Title": "Franklin Faces Additional Charges",
        "Link": "https://www.npr.org/templates/story/story.php?storyId=4702402",
        "Slug": "Law",
        "By": "Larry Abramson"
    },
    {
        "Title": "U.S. HIV Cases Top 1 Million",
        "Link": "https://www.npr.org/2005/06/14/4702405/u-s-hiv-cases-top-1-million",
        "Slug": "Health",
        "By": "Brenda Wilson"
    },
    {
        "Title": "Siblings Work to Reunite Mentally Retarded Family Members",
        "Link": "https://www.npr.org/templates/story/story.php?storyId=4702408",
        "Slug": "Health",
        "By": "Colin Fogarty"
    },
    {
        "MoWeEd Track": "VENETIAN RUSH HOUR",
        "MoWeEd Artists": [
            "GAVIN LURSSEN"
        ]
    },
    {
        "MoWeEd Track": "Nica's Dream",
        "MoWeEd Artists": [
            "Tébar",
            "Ximo"
        ]
    },
    {
        "Title": "Astronomers Find Planet with Similarities to Earth",
        "Link": "https://www.npr.org/templates/story/story.php?storyId=4702411",
        "Slug": "Space",
        "By": "Richard Harris"
    },
    {
        "Title": "'Heartless Bastards' Take Cautious Steps Into Limelight",
        "Link": "https://www.npr.org/templates/story/story.php?storyId=4702414",
        "Slug": "Music Interviews",
        "By": "Steve Inskeep"
    },
    {
        "MoWeEd Track": "Moment Musicale, Op.94: No.3",
        "MoWeEd Artists": [
            "Trio Voronezh"
        ]
    },
    {
        "Title": "Vermont Crusader Mascot Sent Packing",
        "Link": "https://www.npr.org/templates/story/story.php?storyId=4702866",
        "Slug": "Education",
        "By": null
    },
    {
        "Title": "Callers Flood Indonesian President's Mobile Number",
        "Link": "https://www.npr.org/templates/story/story.php?storyId=4702869",
        "Slug": null,
        "By": null
    }
]