[
    {
        "Page Link": "https://www.npr.org/programs/all-things-considered/2011/01/05/132679850/",
        "Edition": "All Things",
        "Date Numbered": "2011-01-05",
        "Day": "Wed",
        "Scanned Date": "2022-02-07 01:57:47"
    },
    {
        "Title": "Boehner Takes Gavel As New House Gets To Work",
        "Link": "https://www.npr.org/2011/01/05/132685257/Boehner-Takes-Gavel-As-New-House-Gets-To-Work",
        "Slug": "Politics",
        "By": "Audie Cornish"
    },
    {
        "Title": "What Lies Ahead For The 112th Congress?",
        "Link": "https://www.npr.org/2011/01/05/132685261/What-Lies-Ahead-For-The-112th-Congress",
        "Slug": "Politics",
        "By": null
    },
    {
        "Title": "Lawmakers Talk Bipartisanship; Will It Last?",
        "Link": "https://www.npr.org/2011/01/05/132685265/Lawmakers-Talk-Bipartisanship-Will-It-Last",
        "Slug": "Politics",
        "By": null
    },
    {
        "ATC Track": "Tree King Creek",
        "ATC Artists": [
            "Psychograss"
        ]
    },
    {
        "ATC Track": "The Last Fool",
        "ATC Artists": [
            "Orgone"
        ]
    },
    {
        "Title": "Coal Mine Safety Enforcement Case Settled",
        "Link": "https://www.npr.org/2011/01/05/132675452/landmark-coal-mine-safety-enforcement-case-settled",
        "Slug": "Mine Safety In America",
        "By": "Howard Berkes"
    },
    {
        "Title": "The Many Lives Of The 'Death Panel'",
        "Link": "https://www.npr.org/sections/health-shots/2011/01/05/132680683/the-many-lives-of-the-death-panel",
        "Slug": "Shots - Health News",
        "By": "Julie Rovner"
    },
    {
        "ATC Track": "Falling Over Evening",
        "ATC Artists": [
            "The Six Parts Seven"
        ]
    },
    {
        "ATC Track": "Concerto In G Minor for Two Cellows, String & Basso Continuo, Rv 531 (3)",
        "ATC Artists": [
            "Yo-yo Ma"
        ]
    },
    {
        "Title": "Senate Democrats Seek Changes To Filibuster Rules",
        "Link": "https://www.npr.org/2011/01/05/132685269/Senate-Democrats-Seek-Changes-To-Filibuster-Rules",
        "Slug": "Politics",
        "By": null
    },
    {
        "Title": "Obama Picks New Nominee For Legal Counsel",
        "Link": "https://www.npr.org/2011/01/05/132681380/obama-picks-new-nominee-for-legal-counsels-office",
        "Slug": "Politics",
        "By": "Carrie Johnson"
    },
    {
        "Title": "Mobile Money Revolution Aids Kenya's Poor",
        "Link": "https://www.npr.org/2011/01/05/132679772/mobile-money-revolution-aids-kenyas-poor-economy",
        "Slug": "Africa",
        "By": "Frank Langfitt"
    },
    {
        "ATC Track": "Fantasies of the Orient",
        "ATC Artists": [
            "Extra Golden"
        ]
    },
    {
        "ATC Track": "Just What I Was Thinking",
        "ATC Artists": [
            "Glorytellers"
        ]
    },
    {
        "Title": "Letters: Supernova Sleuth; Gerry Rafferty",
        "Link": "https://www.npr.org/2011/01/05/132685273/Letters-Supernova-Sleuth-Gerry-Rafferty",
        "Slug": "From Our Listeners",
        "By": null
    },
    {
        "Title": "Training And Trust: Partners On The Flying Trapeze",
        "Link": "https://www.npr.org/2011/01/05/132678699/training-and-trust-partners-on-the-flying-trapeze",
        "Slug": "Performing Arts",
        "By": "Elizabeth Blair"
    },
    {
        "ATC Track": "Sarabande",
        "ATC Artists": [
            "Yo-Yo Ma"
        ]
    },
    {
        "ATC Track": "You Must Be a Lion",
        "ATC Artists": [
            "Marco Benevento"
        ]
    },
    {
        "Title": "112th Congress Gets Under Way",
        "Link": "https://www.npr.org/2011/01/05/132685277/112th-Congress-Gets-Under-Way",
        "Slug": "Politics",
        "By": null
    },
    {
        "Title": "New House Majority Introduces Rules Changes",
        "Link": "https://www.npr.org/2011/01/05/132685281/House-Weighs-Rules-Changes",
        "Slug": "Politics",
        "By": null
    },
    {
        "Title": "13 New Senators Sworn In, As Senate Gets To Work",
        "Link": "https://www.npr.org/2011/01/05/132685285/13-New-Lawmakers-Sworn-In-As-Senators",
        "Slug": "Politics",
        "By": "David Welna"
    },
    {
        "Title": "Utah Sen. Mike Lee Pushes Small Government",
        "Link": "https://www.npr.org/2011/01/05/132685289/Utah-Sen-Mike-Lee-On-Push-To-Repeal-Health-Law",
        "Slug": "Politics",
        "By": null
    },
    {
        "ATC Track": "Pickin' a",
        "ATC Artists": [
            "Lynn Patrick"
        ]
    },
    {
        "ATC Track": "Spankin' It",
        "ATC Artists": [
            "Swamp Rat"
        ]
    },
    {
        "Title": "Sanitized Edition Of 'Huckleberry Finn' Causes Uproar",
        "Link": "https://www.npr.org/2011/01/05/132685293/Sanitized-Edition-Of-Huckleberry-Finn-Causes-Uproar",
        "Slug": "Books",
        "By": "Larry Abramson"
    },
    {
        "Title": "Philadelphia Museum Sells Objects To Get A Face-Lift",
        "Link": "https://www.npr.org/2011/01/05/132678420/in-philadelphia-a-museum-fundraising-controversy",
        "Slug": "Culture",
        "By": "Joel Rose"
    },
    {
        "ATC Track": "A Night in Manarola",
        "ATC Artists": [
            "Stef Burns",
            "D'Agostino",
            "Peppino"
        ]
    },
    {
        "ATC Track": "Samambaia",
        "ATC Artists": [
            "Yo-Yo Ma"
        ]
    },
    {
        "Title": "White House Press Secretary Robert Gibbs Resigns",
        "Link": "https://www.npr.org/2011/01/05/132685297/White-House-Press-Secretary-Robert-Gibbs-Resigns",
        "Slug": "Politics",
        "By": "Mara Liasson"
    },
    {
        "Title": "Pelosi: Midterms Not A Referendum On Health Care",
        "Link": "https://www.npr.org/2011/01/05/132685301/Pelosi-Midterms-Not-A-Referendum-On-Health-Care",
        "Slug": "Politics",
        "By": null
    },
    {
        "Title": "Congressional Kids Crowd The Halls",
        "Link": "https://www.npr.org/2011/01/05/132685305/Congressional-Kids-Crowd-The-Halls",
        "Slug": "Politics",
        "By": null
    },
    {
        "ATC Track": "THE HIGH SCHOOL CADETS",
        "ATC Artists": [
            "BILL KNOPF"
        ]
    },
    {
        "Title": "U.S. Diplomats Fan Out Over Sudan Ahead Of Vote",
        "Link": "https://www.npr.org/2011/01/05/132685309/U-S-Diplomats-Fan-Out-Over-Sudan-Ahead-Of-Vote",
        "Slug": "Africa",
        "By": "Michele Kelemen"
    },
    {
        "ATC Track": "Immaculate Heart, Pt. 2",
        "ATC Artists": [
            "The American Analog Set"
        ]
    },
    {
        "ATC Track": "I Am Not A Farmer",
        "ATC Artists": [
            "Bill Frisell"
        ]
    },
    {
        "Title": "Viral Video Helps Give Homeless Man A New Chance",
        "Link": "https://www.npr.org/2011/01/05/132685313/Homeless-Man-Gets-New-Chance-After-Video-Goes-Viral",
        "Slug": "National",
        "By": null
    },
    {
        "Title": "Marni Nixon: Hollywood's Voice 'Ghost'",
        "Link": "https://www.npr.org/2011/01/05/132685317/marni-nixon-hollywoods-voice-ghost",
        "Slug": "Music Interviews",
        "By": null
    }
]