[
    {
        "Page Link": "https://www.npr.org/programs/weekend-edition-sunday/2010/01/17/122582310/",
        "Edition": "Weekend Edition",
        "Date Numbered": "2010-01-17",
        "Day": "Sun",
        "Scanned Date": "2021-06-07 01:11:30"
    },
    {
        "Title": "At Airport, Aid Flows In But Trickles Out",
        "Link": "https://www.npr.org/templates/story/story.php?storyId=122669127",
        "Slug": "Haiti Quake: Ruin And Recovery",
        "By": "Carrie Kahn"
    },
    {
        "Title": "Haitian Woman: 'All I Have Now' Is A Dress, Grain Bag",
        "Link": "https://www.npr.org/templates/story/story.php?storyId=122671001",
        "Slug": "Haiti Quake: Ruin And Recovery",
        "By": "Jason Beaubien"
    },
    {
        "Title": "USDA's Secretary Gives His Response To Haiti",
        "Link": "https://www.npr.org/templates/story/story.php?storyId=122670927",
        "Slug": "World",
        "By": null
    },
    {
        "MoWeEd Track": "Lilian in the Big Blue",
        "MoWeEd Artists": [
            "Omer Avital"
        ]
    },
    {
        "MoWeEd Track": "Third World Love Story",
        "MoWeEd Artists": [
            "Omer Avital"
        ]
    },
    {
        "Title": "First Week Of Same-Sex Marriage Trial Attracts Buzz",
        "Link": "https://www.npr.org/templates/story/story.php?storyId=122670931",
        "Slug": "Law",
        "By": "Scott Shafer"
    },
    {
        "Title": "Rev. Kyles Remembers Martin Luther King, Jr.",
        "Link": "https://www.npr.org/templates/story/story.php?storyId=122670935",
        "Slug": "Obituaries",
        "By": null
    },
    {
        "Title": "Remembering King And The 'Fierce Urgency Of Now'",
        "Link": "https://www.npr.org/templates/story/story.php?storyId=122610865",
        "Slug": "Remembering Martin Luther King Jr.",
        "By": "E. Ethelbert Miller"
    },
    {
        "Title": "Letters, And A Survey On Social Media Use",
        "Link": "https://www.npr.org/templates/story/story.php?storyId=122670939",
        "Slug": "From Our Listeners",
        "By": null
    },
    {
        "MoWeEd Track": "Knights of Columbus",
        "MoWeEd Artists": [
            "Halloween",
            "Alaska"
        ]
    },
    {
        "MoWeEd Track": "Scratch My Back",
        "MoWeEd Artists": [
            "Killian Mansfield",
            "Dr. John"
        ]
    },
    {
        "Title": "The Bad Pun Department Strikes Again",
        "Link": "https://www.npr.org/templates/story/story.php?storyId=122651308",
        "Slug": "Sunday Puzzle",
        "By": null
    },
    {
        "Title": "Helen Mirren, Acting Out As Tolstoy's Wild Sofya",
        "Link": "https://www.npr.org/templates/story/story.php?storyId=122613323",
        "Slug": "Movie Interviews",
        "By": null
    },
    {
        "MoWeEd Track": "Bagatelle op.30 in D flat Major, Op.30",
        "MoWeEd Artists": [
            "Tomislav Baynov"
        ]
    },
    {
        "MoWeEd Track": "Prelude for Piano in F major, Op.2 No.3",
        "MoWeEd Artists": [
            "Tomislav Baynov"
        ]
    },
    {
        "Title": "Search And Rescue Teams In Haiti Race Against Time",
        "Link": "https://www.npr.org/2010/01/17/122670949/search-and-rescue-teams-in-haiti-race-against-time",
        "Slug": "Haiti Quake: Ruin And Recovery",
        "By": "Jackie Northam"
    },
    {
        "Title": "Yanukovych Leads Ukraine's Presidential Race",
        "Link": "https://www.npr.org/templates/story/story.php?storyId=122670954",
        "Slug": "World",
        "By": "David Greene"
    },
    {
        "MoWeEd Track": "Five Refractions of a Prelude by Bach, for guitar [Variation]",
        "MoWeEd Artists": [
            "Andrew McKenna Lee"
        ]
    },
    {
        "Title": "Obama Celebrates A Year In Office",
        "Link": "https://www.npr.org/templates/story/story.php?storyId=122670958",
        "Slug": "Politics",
        "By": null
    },
    {
        "Title": "Newly Blue Colorado Flirts With Old Flame Red",
        "Link": "https://www.npr.org/templates/story/story.php?storyId=122582280",
        "Slug": "Election 2010",
        "By": "Jeff Brady"
    },
    {
        "Title": "What Is Causing Gas Prices To Go Up?",
        "Link": "https://www.npr.org/templates/story/story.php?storyId=122670964",
        "Slug": "Economy",
        "By": "Marianne Russ"
    },
    {
        "MoWeEd Track": "The Rise and Fall of Flingel Bunt",
        "MoWeEd Artists": [
            "The Shadows"
        ]
    },
    {
        "Title": "Haiti's Influence On U.S. Over The Years, And Now",
        "Link": "https://www.npr.org/templates/story/story.php?storyId=122670968",
        "Slug": "Opinion",
        "By": "Diane Roberts"
    },
    {
        "MoWeEd Track": "Jah Dread",
        "MoWeEd Artists": [
            "Augustus Pablo"
        ]
    },
    {
        "Title": "'Downwinders' Make One Last Push For Money",
        "Link": "https://www.npr.org/templates/story/story.php?storyId=122670972",
        "Slug": "National",
        "By": "Daniel Kraker"
    },
    {
        "Title": "Ringo Starr: The Drums Are Where The Soul Is",
        "Link": "https://www.npr.org/templates/story/story.php?storyId=122620250",
        "Slug": "Music Interviews",
        "By": null
    },
    {
        "MoWeEd Track": "All You Need Is Love",
        "MoWeEd Artists": [
            "The Beatles"
        ]
    },
    {
        "MoWeEd Track": "Fill in the Blanks",
        "MoWeEd Artists": [
            "Ringo Starr"
        ]
    }
]