[
    {
        "Page Link": "https://www.npr.org/programs/all-things-considered/2013/03/10/173852292/",
        "Edition": "All Things",
        "Date Numbered": "2013-03-10",
        "Day": "Sun",
        "Scanned Date": "2022-02-07 02:43:39",
        "Playlist URI": "2fWaHGZB6x58xZT0a55x25",
        "Playlist Link": "https://open.spotify.com/playlist/2fWaHGZB6x58xZT0a55x25",
        "Snapshot ID": "MSxlN2VmZTFmMWMwYzE3MjcxZmViODk5ZWU0NmNjMzE1MTk1NzAwMzg1",
        "Playlist Name": "ATC 2013-03-10 Sun All Things Considered"
    },
    {
        "Title": "Solitary Confinement: Punishment Or Cruelty?",
        "Link": "https://www.npr.org/2013/03/10/173957675/solitary-confinement-punishment-or-cruelty",
        "Slug": "National",
        "By": "NPR Staff"
    },
    {
        "ATC Track": "Forever Lost",
        "ATC Artists": [
            "God Is an Astronaut"
        ],
        "Result Track Name": "Forever Lost",
        "Result Artist Names": [
            "God Is An Astronaut"
        ],
        "Result Track-Match Percent": 1.0,
        "Result Artists-Match Percent": 1.0,
        "Result Track URI": "spotify:track:3p1XieTGbODd1PCYUrcH1Q",
        "Result Album Name": "All Is Violent, All Is Bright (2011 Remastered Edition)"
    },
    {
        "Title": "Once On Death Row, He Now Fights To Defeat The Death Penalty",
        "Link": "https://www.npr.org/2013/03/10/173852138/once-on-death-row-he-now-fights-to-defeat-the-death-penalty",
        "Slug": "Law",
        "By": "Margot Adler"
    },
    {
        "Title": "Are There Too Many Ph.D.s And Not Enough Jobs?",
        "Link": "https://www.npr.org/2013/03/10/173953052/are-there-too-many-phds-and-not-enough-jobs",
        "Slug": "Education",
        "By": null
    },
    {
        "ATC Track": "Impossible Soul",
        "ATC Artists": [
            "Sufjan Stevens"
        ],
        "Result Track Name": "Impossible Soul",
        "Result Artist Names": [
            "Sufjan Stevens"
        ],
        "Result Track-Match Percent": 1.0,
        "Result Artists-Match Percent": 1.0,
        "Result Track URI": "spotify:track:36KKQqcDQTk4Op0usyqrMS",
        "Result Album Name": "The Age of Adz"
    },
    {
        "Title": "Remembering Aldo Leopold, Visionary Conservationist And Writer",
        "Link": "https://www.npr.org/2013/03/10/173949498/remembering-aldo-leopold-visionary-conservationist-and-writer",
        "Slug": "Environment",
        "By": "Jacki Lyden"
    },
    {
        "ATC Track": "Black Hole",
        "ATC Artists": [
            "Shawn Lee"
        ],
        "Result Track Name": "Black Hole",
        "Result Artist Names": [
            "Mosco Lee"
        ],
        "Result Track-Match Percent": 1.0,
        "Result Artists-Match Percent": 0.5,
        "Result Track URI": "spotify:track:5vcNZWdrNCmdua8bDrjW3B",
        "Result Album Name": "Timeless Galaxies EP"
    },
    {
        "Title": "A Twin Carries On Alone In 'Her: A Memoir' ",
        "Link": "https://www.npr.org/2013/03/10/173707927/a-twin-carries-on-alone-in-her-a-memoir",
        "Slug": "Author Interviews",
        "By": "NPR Staff"
    },
    {
        "Title": "'The Last Five Years' Returns To New York",
        "Link": "https://www.npr.org/2013/03/10/173817976/the-last-five-years-returns-to-new-york",
        "Slug": "Theater",
        "By": "NPR Staff"
    },
    {
        "ATC Track": "Veins of Coal",
        "ATC Artists": [
            "The Horse Flies"
        ],
        "Result Track Name": "Veins of Coal",
        "Result Artist Names": [
            "The Horse Flies"
        ],
        "Result Track-Match Percent": 1.0,
        "Result Artists-Match Percent": 1.0,
        "Result Track URI": "spotify:track:2yqpA8q59dOdkpRu7VNTr6",
        "Result Album Name": "Until the Ocean"
    },
    {
        "ATC Track": "Tropicana",
        "ATC Artists": [
            "Ratatat"
        ],
        "Result Track Name": "Tropicana",
        "Result Artist Names": [
            "Ratatat"
        ],
        "Result Track-Match Percent": 1.0,
        "Result Artists-Match Percent": 1.0,
        "Result Track URI": "spotify:track:1roMT9D1qzTffaFWeh9xO1",
        "Result Album Name": "Classics"
    }
]