[
    {
        "Page Link": "https://www.npr.org/programs/all-things-considered/2005/10/27/12973993/",
        "Edition": "All Things",
        "Date Numbered": "2005-10-27",
        "Day": "Thu",
        "Scanned Date": "2022-02-06 23:29:43"
    },
    {
        "Title": "Republican Opposition Made Miers Bid Untenable",
        "Link": "https://www.npr.org/templates/story/story.php?storyId=4978293",
        "Slug": "Harriet Miers Withdraws as High Court Nominee",
        "By": "David Welna"
    },
    {
        "Title": "Understanding the Miers Withdrawal",
        "Link": "https://www.npr.org/templates/story/story.php?storyId=4978296",
        "Slug": "Harriet Miers Withdraws as High Court Nominee",
        "By": "Melissa Block"
    },
    {
        "ATC Track": "VARIATIONS ON WINTER FROM VIVALDI'S FOUR SEASONS: SNOW WHAT?",
        "ATC Artists": [
            "TURTLE ISLAND STRING QUARTET"
        ]
    },
    {
        "ATC Track": "1968",
        "ATC Artists": [
            "Bill Frisell"
        ]
    },
    {
        "Title": "Commission Details Illegal Food-for-Oil Payments",
        "Link": "https://www.npr.org/templates/story/story.php?storyId=4978299",
        "Slug": "World",
        "By": "Corey Flintoff"
    },
    {
        "Title": "Letters: Rosa Parks, Beatles Redux",
        "Link": "https://www.npr.org/templates/story/story.php?storyId=4978302",
        "Slug": "From Our Listeners",
        "By": null
    },
    {
        "ATC Track": "In My Life",
        "ATC Artists": [
            "Ofra Harnoy"
        ]
    },
    {
        "ATC Track": "In My Life",
        "ATC Artists": [
            "Ofra Harnoy"
        ]
    },
    {
        "Title": "The Death of an Iraqi Prisoner",
        "Link": "https://www.npr.org/templates/story/story.php?storyId=4977986",
        "Slug": "World",
        "By": "John McChesney"
    },
    {
        "ATC Track": "The Girl With the Rose Hips",
        "ATC Artists": [
            "Dave Douglas"
        ]
    },
    {
        "Title": "Tracking Miers' Downward Trajectory",
        "Link": "https://www.npr.org/templates/story/story.php?storyId=4978305",
        "Slug": "Harriet Miers Withdraws as High Court Nominee",
        "By": "Don Gonyea"
    },
    {
        "Title": "Senators on Miers' Decision to Withdraw Nomination",
        "Link": "https://www.npr.org/templates/story/story.php?storyId=4978308",
        "Slug": "Harriet Miers Withdraws as High Court Nominee",
        "By": "Robert Siegel"
    },
    {
        "ATC Track": "Marwa Blues",
        "ATC Artists": [
            "George Harrison"
        ]
    },
    {
        "Title": "Conservative Columnist's Miers Plan Played Out",
        "Link": "https://www.npr.org/templates/story/story.php?storyId=4978311",
        "Slug": "Harriet Miers Withdraws as High Court Nominee",
        "By": "Melissa Block"
    },
    {
        "Title": "NYC Mayoral Challenger Gets Message Out in a Big Way",
        "Link": "https://www.npr.org/templates/story/story.php?storyId=4978314",
        "Slug": "National",
        "By": "Robert Smith"
    },
    {
        "ATC Track": "Motown Mash",
        "ATC Artists": [
            "James Carter"
        ]
    },
    {
        "Title": "Lines, Power Outages Still Plague South Florida",
        "Link": "https://www.npr.org/templates/story/story.php?storyId=4978317",
        "Slug": "Katrina & Beyond",
        "By": "Melissa Block"
    },
    {
        "Title": "California Mulls Power to Draw Legislative Districts",
        "Link": "https://www.npr.org/templates/story/story.php?storyId=4978320",
        "Slug": "National",
        "By": "Ina Jaffe"
    },
    {
        "Title": "Army Spc. Lucas Frantz, A Kansan Football Hero",
        "Link": "https://www.npr.org/templates/story/story.php?storyId=4978323",
        "Slug": "The Impact of War",
        "By": "Greg Allen"
    },
    {
        "ATC Track": "Triptico",
        "ATC Artists": [
            "Gotan Project"
        ]
    },
    {
        "ATC Track": "Time",
        "ATC Artists": [
            "Vernon Reid"
        ]
    },
    {
        "Title": "Exxon Mobil Posts Record-High Profits",
        "Link": "https://www.npr.org/templates/story/story.php?storyId=4978326",
        "Slug": "Paying at the Pump",
        "By": "Scott Horsley"
    },
    {
        "Title": "'60s Icon Donovan Returns with 'Try for the Sun'",
        "Link": "https://www.npr.org/templates/story/story.php?storyId=4978990",
        "Slug": "Music Reviews",
        "By": "David Greenberger"
    },
    {
        "ATC Track": "Bioshock: Welcome to Rapture",
        "ATC Artists": [
            "Please Check Back In a Few Days"
        ]
    },
    {
        "ATC Track": "These Arms of Mine",
        "ATC Artists": [
            "Joe Goldmark"
        ]
    }
]