[
    {
        "Page Link": "https://www.npr.org/programs/all-things-considered/1997/09/24/12986313/",
        "Edition": "All Things",
        "Date Numbered": "1997-09-24",
        "Day": "Wed",
        "Scanned Date": "2022-02-06 18:59:22",
        "Playlist URI": "4Ukx80SBByYOgvWo5YxduJ",
        "Playlist Link": "https://open.spotify.com/playlist/4Ukx80SBByYOgvWo5YxduJ",
        "Snapshot ID": "MSw2MmQ3Zjk4ZTIyOTA0NGZiNGZkYjExNjFhNTNjMjAxMmYyYjFiZjJl",
        "Playlist Name": "ATC 1997-09-24 Wed All Things Considered"
    },
    {
        "Title": "Irs Hearings",
        "Link": "https://www.npr.org/1997/09/24/1037963/irs-hearings",
        "Slug": null,
        "By": null
    },
    {
        "Title": "Tax Box",
        "Link": "https://www.npr.org/1997/09/24/1037964/tax-box",
        "Slug": null,
        "By": null
    },
    {
        "Title": "Kids & Guns",
        "Link": "https://www.npr.org/1997/09/24/1037965/kids-guns",
        "Slug": null,
        "By": null
    },
    {
        "Title": "Other Stories",
        "Link": "https://www.npr.org/1997/09/24/1037966/other-stories",
        "Slug": null,
        "By": null
    },
    {
        "Title": "India & Pakistan Talks",
        "Link": "https://www.npr.org/1997/09/24/1037967/india-pakistan-talks",
        "Slug": null,
        "By": null
    },
    {
        "Title": "Least Developed Countries",
        "Link": "https://www.npr.org/1997/09/24/1037968/least-developed-countries",
        "Slug": null,
        "By": null
    },
    {
        "Title": "Shali Swan Song",
        "Link": "https://www.npr.org/1997/09/24/1037969/shali-swan-song",
        "Slug": null,
        "By": null
    },
    {
        "Title": "Yeltsin's Speech",
        "Link": "https://www.npr.org/1997/09/24/1037970/yeltsins-speech",
        "Slug": null,
        "By": null
    },
    {
        "Title": "Augustus Bustus",
        "Link": "https://www.npr.org/1997/09/24/1037971/augustus-bustus",
        "Slug": null,
        "By": null
    },
    {
        "Title": "Debbie Friedman",
        "Link": "https://www.npr.org/1997/09/24/1037972/debbie-friedman",
        "Slug": null,
        "By": null
    },
    {
        "Title": "Clinton & Labor",
        "Link": "https://www.npr.org/1997/09/24/1037973/clinton-labor",
        "Slug": null,
        "By": null
    },
    {
        "Title": "Fbi Most Wanted",
        "Link": "https://www.npr.org/1997/09/24/1037974/fbi-most-wanted",
        "Slug": null,
        "By": null
    },
    {
        "Title": "Ohio Death Row",
        "Link": "https://www.npr.org/1997/09/24/1037975/ohio-death-row",
        "Slug": null,
        "By": null
    },
    {
        "Title": "Other Stories",
        "Link": "https://www.npr.org/1997/09/24/1037976/other-stories",
        "Slug": null,
        "By": null
    },
    {
        "Title": "Salomon Sold",
        "Link": "https://www.npr.org/1997/09/24/1037977/salomon-sold",
        "Slug": null,
        "By": null
    },
    {
        "Title": "Tuition & Financial Aid",
        "Link": "https://www.npr.org/1997/09/24/1037978/tuition-financial-aid",
        "Slug": null,
        "By": null
    },
    {
        "Title": "Underwriters Laboratories",
        "Link": "https://www.npr.org/1997/09/24/1037979/underwriters-laboratories",
        "Slug": null,
        "By": null
    },
    {
        "Title": "Rolling Stones Reviewed",
        "Link": "https://www.npr.org/1997/09/24/1037980/rolling-stones-reviewed",
        "Slug": null,
        "By": null
    },
    {
        "Title": "Cookwise",
        "Link": "https://www.npr.org/1997/09/24/1037981/cookwise",
        "Slug": null,
        "By": null
    }
]