[
    {
        "Page Link": "https://www.npr.org/programs/morning-edition/2003/10/27/13060636/",
        "Edition": "Morning Edition",
        "Date Numbered": "2003-10-27",
        "Day": "Mon",
        "Scanned Date": "2021-05-29 15:51:17"
    },
    {
        "Title": "Baghdad Bombings Kill Dozens",
        "Link": "https://www.npr.org/templates/story/story.php?storyId=1480001",
        "Slug": "World",
        "By": "Jacki Lyden"
    },
    {
        "Title": "California Fires Kill 13",
        "Link": "https://www.npr.org/templates/story/story.php?storyId=1480003",
        "Slug": "National",
        "By": null
    },
    {
        "MoWeEd Track": "Alone Together",
        "MoWeEd Artists": [
            "Bob James",
            "Joe Sample"
        ]
    },
    {
        "MoWeEd Track": "3:00 Am Blues",
        "MoWeEd Artists": [
            "Dick Hyman Group Featuring Howard Alden"
        ]
    },
    {
        "Title": "Economists Mixed on Looming Growth Report ",
        "Link": "https://www.npr.org/templates/story/story.php?storyId=1480005",
        "Slug": "Business",
        "By": "Jim Zarroli"
    },
    {
        "Title": "Brawney Man",
        "Link": "https://www.npr.org/templates/story/story.php?storyId=1480007",
        "Slug": "Business",
        "By": null
    },
    {
        "MoWeEd Track": "Everything Is Chaning",
        "MoWeEd Artists": [
            "Declassified"
        ]
    },
    {
        "Title": "Morning Edition Returns: World RPS Champion",
        "Link": "https://www.npr.org/templates/story/story.php?storyId=1480121",
        "Slug": null,
        "By": null
    },
    {
        "Title": "Russian Oil Tycoon Arrested",
        "Link": "https://www.npr.org/templates/story/story.php?storyId=1480009",
        "Slug": "World",
        "By": "Lawrence Sheets"
    },
    {
        "MoWeEd Track": "Street of Dreams",
        "MoWeEd Artists": [
            "Oliver Jones"
        ]
    },
    {
        "Title": "Dem. Candidates Attack Bush",
        "Link": "https://www.npr.org/templates/story/story.php?storyId=1480011",
        "Slug": "National",
        "By": "Mara Liasson"
    },
    {
        "Title": "Listener Letters",
        "Link": "https://www.npr.org/templates/story/story.php?storyId=1480013",
        "Slug": null,
        "By": null
    },
    {
        "MoWeEd Track": "The Tulip and the Acorn",
        "MoWeEd Artists": [
            "Alex Grant"
        ]
    },
    {
        "Title": "MIT Students Develop Online Music Sharing System",
        "Link": "https://www.npr.org/templates/story/story.php?storyId=1480015",
        "Slug": "National",
        "By": "Chris Arnold"
    },
    {
        "Title": "Computational Origami: Not Just Paper Swans",
        "Link": "https://www.npr.org/templates/story/story.php?storyId=1480017",
        "Slug": "Science",
        "By": null
    },
    {
        "MoWeEd Track": "Raquel",
        "MoWeEd Artists": [
            "Bau"
        ]
    },
    {
        "MoWeEd Track": "Concerto In G Major: Allegro",
        "MoWeEd Artists": [
            "Empire Brass Quintet With William Kuhlman"
        ]
    },
    {
        "Title": "California Fires: San Bernardino",
        "Link": "https://www.npr.org/templates/story/story.php?storyId=1480019",
        "Slug": null,
        "By": "Carrie Kahn"
    },
    {
        "Title": "Morning Edition Returns: Lost Loot & Foot Fraud",
        "Link": "https://www.npr.org/templates/story/story.php?storyId=1480129",
        "Slug": null,
        "By": null
    },
    {
        "Title": "Politics with Cokie Roberts",
        "Link": "https://www.npr.org/templates/story/story.php?storyId=1480021",
        "Slug": null,
        "By": "Cokie Roberts"
    },
    {
        "MoWeEd Track": "Heartburn Waltz [#]",
        "MoWeEd Artists": [
            "Vince Guaraldi Trio"
        ]
    },
    {
        "MoWeEd Track": "Sunday",
        "MoWeEd Artists": [
            "Ray Brown"
        ]
    },
    {
        "Title": "Presidential Power",
        "Link": "https://www.npr.org/templates/story/story.php?storyId=1480023",
        "Slug": null,
        "By": null
    },
    {
        "Title": "Commentary: Remaking Iraq",
        "Link": "https://www.npr.org/templates/story/story.php?storyId=1480025",
        "Slug": null,
        "By": null
    },
    {
        "MoWeEd Track": "Interface",
        "MoWeEd Artists": [
            "Hank Jones"
        ]
    },
    {
        "Title": "Pasta, Bread Makers Fight Low-Carb Diets",
        "Link": "https://www.npr.org/templates/story/story.php?storyId=1477340",
        "Slug": "Science",
        "By": "Greg Allen"
    },
    {
        "MoWeEd Track": "The Country Open",
        "MoWeEd Artists": [
            "The Jazz Mandolin Project"
        ]
    },
    {
        "Title": "Episcopal Church at a Crossroads",
        "Link": "https://www.npr.org/templates/story/story.php?storyId=1480027",
        "Slug": "National",
        "By": "Barbara Bradley Hagerty"
    },
    {
        "Title": "Maine to Vote on Casino Gambling",
        "Link": "https://www.npr.org/templates/story/story.php?storyId=1480029",
        "Slug": "National",
        "By": null
    },
    {
        "MoWeEd Track": "Ceora",
        "MoWeEd Artists": [
            "Flutology"
        ]
    },
    {
        "MoWeEd Track": "Cantaloupe Island",
        "MoWeEd Artists": [
            "Herbie Hancock"
        ]
    },
    {
        "Title": "'Prairie Diaries': Amber Peterman",
        "Link": "https://www.npr.org/templates/story/story.php?storyId=1478020",
        "Slug": null,
        "By": null
    },
    {
        "MoWeEd Track": "Autumn Leaves",
        "MoWeEd Artists": [
            "Martin Taylor"
        ]
    },
    {
        "MoWeEd Track": "East of the Sun",
        "MoWeEd Artists": [
            "Martin Taylor"
        ]
    },
    {
        "Title": "Bank of America Eyes Fleet",
        "Link": "https://www.npr.org/templates/story/story.php?storyId=1480212",
        "Slug": "Business",
        "By": "Jack Speer"
    },
    {
        "MoWeEd Track": "Green's Blues",
        "MoWeEd Artists": [
            "Benny Green"
        ]
    }
]