[
    {
        "Page Link": "https://www.npr.org/programs/all-things-considered/2002/07/27/13037554/",
        "Edition": "All Things",
        "Date Numbered": "2002-07-27",
        "Day": "Sat",
        "Scanned Date": "2022-02-06 21:47:13"
    },
    {
        "Title": "Mining Update",
        "Link": "https://www.npr.org/templates/story/story.php?storyId=1147388",
        "Slug": null,
        "By": null
    },
    {
        "ATC Track": "Riding the Nuclear Tiger",
        "ATC Artists": [
            "Ben Allison"
        ]
    },
    {
        "Title": "Working Longer",
        "Link": "https://www.npr.org/templates/story/story.php?storyId=1147389",
        "Slug": null,
        "By": null
    },
    {
        "ATC Track": "Elizabeth on the Bathroom Floor",
        "ATC Artists": [
            "Eels"
        ]
    },
    {
        "Title": "Budget Woes",
        "Link": "https://www.npr.org/templates/story/story.php?storyId=1147390",
        "Slug": null,
        "By": null
    },
    {
        "ATC Track": "Bemsha Swing/Lively Up Yourself",
        "ATC Artists": [
            "Medeski",
            "Martin",
            "Wood"
        ]
    },
    {
        "Title": "D.C. Mayor's Ballot Problems",
        "Link": "https://www.npr.org/templates/story/story.php?storyId=1147391",
        "Slug": null,
        "By": null
    },
    {
        "Title": "Monitor Raising",
        "Link": "https://www.npr.org/templates/story/story.php?storyId=1147392",
        "Slug": null,
        "By": null
    },
    {
        "ATC Track": "Chubb Sub",
        "ATC Artists": [
            "Medeski",
            "Martin",
            "Wood"
        ]
    },
    {
        "ATC Track": "LADY DELAY",
        "ATC Artists": [
            "DAAU"
        ]
    },
    {
        "ATC Track": "Rossa Blanco",
        "ATC Artists": [
            "Seksu Roba"
        ]
    },
    {
        "Title": "Iraq Opposition",
        "Link": "https://www.npr.org/templates/story/story.php?storyId=1147393",
        "Slug": null,
        "By": null
    },
    {
        "ATC Track": "The Robots",
        "ATC Artists": [
            "Kraftwerk"
        ]
    },
    {
        "Title": "Torture Cases",
        "Link": "https://www.npr.org/templates/story/story.php?storyId=1147394",
        "Slug": null,
        "By": null
    },
    {
        "Title": "Punk Essay",
        "Link": "https://www.npr.org/templates/story/story.php?storyId=1147395",
        "Slug": null,
        "By": null
    },
    {
        "Title": "Future Bikers",
        "Link": "https://www.npr.org/templates/story/story.php?storyId=1147396",
        "Slug": null,
        "By": null
    },
    {
        "Title": "Jellyfish Package",
        "Link": "https://www.npr.org/templates/story/story.php?storyId=1147397",
        "Slug": null,
        "By": null
    },
    {
        "ATC Track": "Computer Love",
        "ATC Artists": [
            "Kraftwerk"
        ]
    }
]